rad_tools-1.0.1.dist-info/licenses/LICENSE.txt
radtools/__init__.py
radtools/__main__.py
radtools/_license.py
radtools/_osfix.py
radtools/_redirect.py
radtools/constants.py
radtools/geometry.py
radtools/numerical.py
radtools/crystal/__init__.py
radtools/crystal/atom.py
radtools/crystal/cell.py
radtools/crystal/crystal.py
radtools/crystal/identify.py
radtools/crystal/kpoints.py
radtools/crystal/lattice.py
radtools/crystal/lattice_plotter.py
radtools/crystal/properties.py
radtools/crystal/bravais_lattice/__init__.py
radtools/crystal/bravais_lattice/constructor.py
radtools/crystal/bravais_lattice/examples.py
radtools/crystal/bravais_lattice/hs_points.py
radtools/crystal/bravais_lattice/standardize.py
radtools/crystal/bravais_lattice/variations.py
radtools/decorate/__init__.py
radtools/decorate/array.py
radtools/decorate/axes.py
radtools/decorate/colormap.py
radtools/decorate/stats.py
radtools/dos/__init__.py
radtools/dos/dos.py
radtools/dos/fatbands_plotting.py
radtools/dos/pdos.py
radtools/dos/pdos_plotting.py
radtools/dos/plotting.py
radtools/io/__init__.py
radtools/io/internal.py
radtools/io/tb2j.py
radtools/io/vampire.py
radtools/io/vasp.py
radtools/magnons/__init__.py
radtools/magnons/diagonalization.py
radtools/magnons/dispersion.py
radtools/score/__init__.py
radtools/score/extract_tb2j.py
radtools/score/identify_wannier_centres.py
radtools/score/make_template.py
radtools/score/plot_dos.py
radtools/score/plot_fatbands.py
radtools/score/plot_tb2j.py
radtools/score/plot_tb2j_magnons.py
radtools/spinham/__init__.py
radtools/spinham/hamiltonian.py
radtools/spinham/parameter.py
rad_tools-1.0.1.dist-info/METADATA
rad_tools-1.0.1.dist-info/WHEEL
rad_tools-1.0.1.dist-info/entry_points.txt
rad_tools-1.0.1.dist-info/top_level.txt
rad_tools-1.0.1.dist-info/RECORD
