Metadata-Version: 2.4
Name: rad-tools
Version: 1.0.1
Summary: Sandbox (mainly condense matter plotting)
Author-email: Andrey Rybakov <rybakov.ad@icloud.com>
License: MIT license
Project-URL: Homepage, https://rad-tools.org
Project-URL: Documentation, https://rad-tools.org
Project-URL: Repository, https://github.com/adrybakov/rad-tools.git
Project-URL: Issues, https://github.com/adrybakov/rad-tools/issues
Project-URL: Changelog, https://rad-tools.org/en/stable/release-notes/index.html
Classifier: Development Status :: 4 - Beta
Classifier: Intended Audience :: Science/Research
Classifier: Intended Audience :: Developers
Classifier: Programming Language :: Python
Classifier: Programming Language :: Python :: 3
Classifier: Programming Language :: Python :: 3.9
Classifier: Programming Language :: Python :: 3.10
Classifier: Programming Language :: Python :: 3.11
Classifier: Programming Language :: Python :: 3.12
Classifier: Programming Language :: Python :: 3.13
Classifier: Programming Language :: Python :: 3 :: Only
Classifier: Topic :: Software Development
Classifier: Topic :: Scientific/Engineering
Classifier: Operating System :: OS Independent
Classifier: License :: OSI Approved :: GNU General Public License v3 (GPLv3)
Requires-Python: >=3.9
License-File: LICENSE.txt
Requires-Dist: numpy
Requires-Dist: matplotlib
Requires-Dist: scipy
Requires-Dist: tqdm
Requires-Dist: termcolor
Dynamic: license-file
